{
  "last_updated": "2026-02-23T19:13:17.718807",
  "total_runs": 2,
  "dates": [
    {
      "date": "2026-02-23",
      "total_steps": 2,
      "successful_steps": 2,
      "failed_steps": 0,
      "total_duration": 0.04,
      "total_errors": 0,
      "total_warnings": 0,
      "status": "success"
    },
    {
      "date": "2026-02-22",
      "total_steps": 5,
      "successful_steps": 5,
      "failed_steps": 0,
      "total_duration": 0.54,
      "total_errors": 0,
      "total_warnings": 2,
      "status": "success"
    }
  ]
}